[{"date":"2015-01-02","key":"Ecnonomy","value":515},{"date":"2015-01-02","key":"Education","value":515},{"date":"2015-01-02","key":"Sports","value":515},{"date":"2015-01-02","key":"Tec","value":515},{"date":"2015-01-03","key":"Ecnonomy","value":1350},{"date":"2015-01-03","key":"Education","value":1350},{"date":"2015-01-03","key":"Sports","value":1350},{"date":"2015-01-03","key":"Tec","value":1350},{"date":"2015-01-04","key":"Ecnonomy","value":433},{"date":"2015-01-04","key":"Education","value":433},{"date":"2015-01-04","key":"Sports","value":433},{"date":"2015-01-04","key":"Tec","value":433},{"date":"2015-01-05","key":"Ecnonomy","value":741},{"date":"2015-01-05","key":"Education","value":741},{"date":"2015-01-05","key":"Sports","value":741},{"date":"2015-01-05","key":"Tec","value":741},{"date":"2015-01-06","key":"Ecnonomy","value":1021},{"date":"2015-01-06","key":"Education","value":1021},{"date":"2015-01-06","key":"Sports","value":1021},{"date":"2015-01-06","key":"Tec","value":1021},{"date":"2015-01-07","key":"Ecnonomy","value":600},{"date":"2015-01-07","key":"Education","value":600},{"date":"2015-01-07","key":"Sports","value":600},{"date":"2015-01-07","key":"Tec","value":600},{"date":"2015-01-08","key":"Ecnonomy","value":1335},{"date":"2015-01-08","key":"Education","value":1335},{"date":"2015-01-08","key":"Sports","value":1335},{"date":"2015-01-08","key":"Tec","value":1335},{"date":"2015-01-09","key":"Ecnonomy","value":388},{"date":"2015-01-09","key":"Education","value":388},{"date":"2015-01-09","key":"Sports","value":388},{"date":"2015-01-09","key":"Tec","value":388},{"date":"2015-01-10","key":"Ecnonomy","value":443},{"date":"2015-01-10","key":"Education","value":443},{"date":"2015-01-10","key":"Sports","value":443},{"date":"2015-01-10","key":"Tec","value":443}]